odoo/addons/easy_my_coop_es_website/README.rst
odoo/addons/easy_my_coop_es_website/__init__.py
odoo/addons/easy_my_coop_es_website/__manifest__.py
odoo/addons/easy_my_coop_es_website/i18n/easy_my_coop_es_website.pot
odoo/addons/easy_my_coop_es_website/readme/CONTRIBUTORS.rst
odoo/addons/easy_my_coop_es_website/readme/DESCRIPTION.rst
odoo/addons/easy_my_coop_es_website/static/description/index.html
odoo/addons/easy_my_coop_es_website/views/become_company_cooperator_view.xml
odoo/addons/easy_my_coop_es_website/views/become_cooperator_view.xml
odoo12_addon_easy_my_coop_es_website-12.0.0.1.0.dist-info/METADATA
odoo12_addon_easy_my_coop_es_website-12.0.0.1.0.dist-info/WHEEL
odoo12_addon_easy_my_coop_es_website-12.0.0.1.0.dist-info/top_level.txt
odoo12_addon_easy_my_coop_es_website-12.0.0.1.0.dist-info/RECORD
