Metadata-Version: 2.1
Name: odoo12-addon-easy-my-coop-es-website
Version: 12.0.0.1.0
Summary: Easy My Coop Website localization for Spain
Home-page: https://coopiteasy.be
Author: Coop IT Easy SCRLfs, Coopdevs Treball SCCL
License: AGPL-3
Platform: UNKNOWN
Classifier: Programming Language :: Python
Classifier: Framework :: Odoo
Classifier: Framework :: Odoo :: 12.0
Classifier: License :: OSI Approved :: GNU Affero General Public License v3
Requires-Python: >=3.5
Requires-Dist: odoo12-addon-easy-my-coop-website (>=12.0.1.0.6)
Requires-Dist: odoo12-addon-easy-my-coop-es
Requires-Dist: odoo (<12.1dev,>=12.0a)
